rabbitmq_pdfparser/__init__.py
rabbitmq_pdfparser-1.0.1.data/scripts/rabbitmq-pdfparser
rabbitmq_pdfparser-1.0.1.dist-info/LICENSE
rabbitmq_pdfparser-1.0.1.dist-info/METADATA
rabbitmq_pdfparser-1.0.1.dist-info/WHEEL
rabbitmq_pdfparser-1.0.1.dist-info/top_level.txt
rabbitmq_pdfparser-1.0.1.dist-info/RECORD
