Metadata-Version: 2.1
Name: rabbitmq-pdfparser
Version: 1.0.1
Summary: Asynchronous job library that consume RabbitMQ for PDF urls and publish pdf text back.
Home-page: UNKNOWN
Author: Furkan Kalkan
Author-email: furkankalkan@mantis.com.tr
License: UNKNOWN
Platform: all
Classifier: License :: OSI Approved :: Apache Software License
Classifier: Topic :: Internet
Classifier: Topic :: Software Development
Classifier: Topic :: Software Development :: Libraries
Classifier: Topic :: Software Development :: Testing
Classifier: Intended Audience :: Developers
Classifier: Operating System :: MacOS
Classifier: Operating System :: POSIX
Classifier: Operating System :: Microsoft
Classifier: Programming Language :: Python
Classifier: Programming Language :: Python :: 3
Classifier: Programming Language :: Python :: 3.6
Classifier: Programming Language :: Python :: 3.7
Classifier: Programming Language :: Python :: 3.8
Requires-Python: >3.6.*, <4
Requires-Dist: aiohttp
Requires-Dist: aio-pika
Requires-Dist: PyPDF2
